{
  "title": "File:Puerto Montt, Chile 2005.jpg",
  "url": "https://upload.wikimedia.org/wikipedia/commons/thumb/8/83/Puerto_Montt%2C_Chile_2005.jpg/1280px-Puerto_Montt%2C_Chile_2005.jpg",
  "original_url": "https://upload.wikimedia.org/wikipedia/commons/8/83/Puerto_Montt%2C_Chile_2005.jpg",
  "license": "CC BY-SA 2.0",
  "license_url": "https://creativecommons.org/licenses/by-sa/2.0",
  "author": "Rui Bittencourt",
  "description": "Puerto Montt",
  "commons_url": "https://commons.wikimedia.org/wiki/File%3APuerto%20Montt%2C%20Chile%202005.jpg"
}