{
  "source": "Library of Congress, Prints & Photographs Division",
  "artist": "Pillsbury & Cleveland Co.",
  "license": "No known restrictions on publication (public domain \u2014 pre-1928)",
  "licenseUrl": "https://www.loc.gov/rr/print/195_copr.html",
  "dateTaken": "1899",
  "sourceUrl": "https://www.loc.gov/item/2006690348/",
  "title": "Skagway, Alaska, 1899",
  "description": "1899 panoramic photograph of the Skagway waterfront and dock during the Klondike Gold Rush era, showing the railroad wharf, steamships, and snow-capped mountains behind the town.",
  "alt": "Panoramic view of the Skagway waterfront in 1899 during the Klondike Gold Rush, with steamships at the railroad wharf and snow-capped mountains behind",
  "verifiedBySession": "2026-04-12 \u2014 downloaded from tile.loc.gov and visually confirmed"
}
