{
  "title": "File:Bodrum 5 (256451574).jpg",
  "url": "https://upload.wikimedia.org/wikipedia/commons/thumb/c/ca/Bodrum_5_%28256451574%29.jpg/1280px-Bodrum_5_%28256451574%29.jpg",
  "original_url": "https://upload.wikimedia.org/wikipedia/commons/c/ca/Bodrum_5_%28256451574%29.jpg",
  "width": 1200,
  "height": 800,
  "license": "CC BY 2.0",
  "license_url": "https://creativecommons.org/licenses/by/2.0",
  "author": "<a rel=\"nofollow\" class=\"external text\" href=\"https://www.flickr.com/people/69024001@N00\">Andy / Andrew Fogg</a> from near Cambridge, UK",
  "description": "A rather careworn water taxi.  I liked the way the sunlight picked out the textures.",
  "commons_url": "https://commons.wikimedia.org/wiki/File%3ABodrum%205%20%28256451574%29.jpg"
}