{
  "ship": "Sky Princess",
  "ship_class": "Royal Class",
  "cruise_line": "Princess Cruises",
  "last_updated": "2026-02-12",
  "content_protocol": "ICP-Lite v1.4",
  "stories": [
    {
      "title": "Sky Suites: The Largest at Sea",
      "persona_label": "Luxury Feature",
      "persona": "luxury",
      "intended_reader": "Travelers interested in premium accommodations",
      "core_insight": "Sky Princess introduced the Sky Suites — two-deck accommodations with largest balconies at sea",
      "markdown": "**Sky Princess debuted in 2019 with a headline feature that redefined what balcony means at sea: the Sky Suites, offering two-deck living space and private outdoor terraces exceeding 1,000 square feet. I'd reviewed luxury cruise accommodations for fifteen years. Nothing I'd seen prepared me for the moment I stepped onto that balcony and realised I was standing on a private sundeck suspended above the ocean.**\n\nThe trajectory of cruise suite design has followed a predictable arc: larger cabins, better views, upgraded amenities, premium service. Each iteration offered more of the same — bigger versions of what came before. Sky Suites broke the pattern by offering something genuinely different: outdoor living space at sea. Not a balcony where you sit. A terrace where you live.\n\nThe tension in that distinction deserves examination. Traditional cruise balconies serve a specific function — you step outside, lean on the railing, watch the ocean, return inside. They're viewing platforms. Sky Suites' upper-level terrace is something else entirely: a private sundeck with dining furniture, loungers, and enough space to host a dozen friends for cocktails without anyone standing. The balcony doesn't supplement the cabin. It becomes the cabin's primary living space, weather permitting.\n\nThe lower level provides conventional luxury — a spacious living area, premium bedding, thoughtful amenities positioned where guests actually reach rather than where designers found photogenic placement. The bathroom offers the marble and rainfall shower that suite passengers expect. Nothing revolutionary here. Solid execution of familiar premium concepts.\n\nBut that upper deck transforms the entire accommodation philosophy. I ate breakfast there each morning, watching Mediterranean coastline slide past while morning sun warmed the teak. I hosted pre-dinner drinks for six friends who'd sailed with me — everyone comfortably seated, the open sky above us, the ocean providing both soundtrack and backdrop. The space eliminated the primary compromise of cruise suite living: the inability to truly live outdoors without sharing the pool deck with thousands of fellow passengers.\n\nThe Sanctuary — Princess's adults-only retreat — operates beautifully aboard Sky Princess, but Sky Suite guests may find themselves choosing their private terrace over shared amenities. When your personal outdoor space exceeds what most resort hotel rooms offer in total square footage, the calculus of where to spend sea days shifts dramatically.\n\nMedallionClass technology integrates throughout the suite experience with the touchless precision the platform provides fleet-wide. The Medallion's cabin-proximity sensing works particularly well for suite guests juggling multiple levels of their accommodation — no fumbling with keys while carrying morning coffee up the internal staircase to the upper deck.\n\nCrown Grill and Sabatini's remain available for specialty dining, and the main dining room delivers Princess's reliable quality. But Sky Suite guests can arrange in-suite dining with a legitimacy that standard cabin room service cannot match — the space accommodates a proper dinner table, the balcony accommodates a proper setting, and the result feels less like room service and more like a private restaurant.\n\nPrincess positioned Sky Suites strategically within their fleet hierarchy. They're not competing with ultra-luxury line suites on butler service or champagne budgets. They're competing on what no other mainstream line offers: genuine outdoor living space at sea. The proposition is specific and compelling — not the most lavish suite afloat, but arguably the most livable.\n\nFor travelers who define luxury as experience rather than thread count, Sky Suites represent something genuinely new. The largest balconies at sea aren't a marketing claim to be verified and dismissed. They're a lived reality that changes how you inhabit a cruise ship.\n\nMovies Under the Stars still drew me to the pool deck on several evenings — the communal outdoor cinema experience offers something private viewing cannot. But returning afterward to my private terrace, watching stars from a space that belonged to me alone, I understood what Sky Suites had achieved: not just a premium cabin but a premium relationship with the ocean itself.\n\n**The lesson:** True luxury isn't about having more of the same — it's about having something genuinely different, and the ships brave enough to reimagine what accommodation means create experiences that no amount of upgrade can replicate.",
      "author": {
        "name": "Luxury Travel Magazine",
        "location": "New York, NY"
      }
    },
    {
      "title": "Europe from Southampton",
      "persona_label": "UK Deployment",
      "persona": "veteran",
      "intended_reader": "UK-based travelers seeking convenient European cruising",
      "core_insight": "Sky Princess frequently homeports from Southampton for European itineraries",
      "markdown": "**Sky Princess regularly operates from Southampton, and after thirty years of flying to Florida or Barcelona to board cruise ships, the morning I drove from our home in Hampshire to the port in forty minutes and walked aboard a Royal Class ship without a single flight, I understood what British cruisers had been waiting for: world-class cruising that starts at home.**\n\nThe significance of Southampton homeporting requires context that non-British cruisers may not appreciate. For decades, premium cruise travel from the UK demanded international flights — Heathrow to Miami, Gatwick to Barcelona, connecting through airports designed to test patience rather than facilitate travel. The flight itself consumed a day. Jet lag consumed another. By the time your cruise vacation actually began, you'd already invested forty-eight hours of stress and exhaustion as the entrance fee. Southampton eliminated that tax entirely.\n\nSky Princess sailing from Southampton reaches European diversity that rivals any global deployment. Norwegian fjords in summer — those dramatic granite walls rising from water so still they create mirror reflections, viewed from the SeaWalk's glass floor while clouds drift beneath your feet. Mediterranean warmth for autumn and spring itineraries — Barcelona's architecture, Rome's history, Greek islands whose whitewashed villages cascade down hillsides like spilled milk. Baltic capitals for those seeking cultural depth — St. Petersburg's palaces, Stockholm's islands, Copenhagen's design elegance. The itinerary range from a single homeport impressed even our well-travelled dinner companions.\n\nThe passenger mix shifts on Southampton sailings in ways that enhance the experience for British travellers. More UK passengers naturally, creating a social atmosphere that feels familiar rather than foreign. More European passengers generally, adding cosmopolitan flavour without the cultural adjustment that American-dominant sailings sometimes require. The atmosphere reflects this diversity — perhaps slightly more formal, certainly more international, with dinner conversations that move between languages and cultural references with the ease of people who've grown up in proximity to different nations.\n\nRoyal Class quality translates perfectly to European waters. The Piazza atrium functions identically whether the ship left Barcelona or Southampton — that signature Princess social space provides the same cafe atmosphere, the same comfortable seating, the same live music that draws passengers together regardless of deployment. MedallionClass technology operates with the same touchless efficiency. Princess service standards maintain regardless of homeport. The ship that sails European itineraries from Southampton is the same ship — same quality, same capability, same crew standards — that sails Caribbean itineraries from Fort Lauderdale.\n\nThe Sanctuary adults-only retreat provided particular value during sea days in the English Channel and Bay of Biscay — stretches that can test passengers with less-than-tropical weather. The sheltered loungers, attentive service, and cushioned peace offered refuge that the open pool deck couldn't always match in British waters.\n\nCrown Grill's steakhouse delivered the same premium dining experience we'd enjoyed on previous Princess sailings from American ports — confirming that homeport does not affect kitchen quality. Sabatini's Italian evenings provided the Mediterranean warmth that British weather sometimes fails to deliver. The main dining room rotated menus with range sufficient for voyages lasting up to two weeks.\n\nMovies Under the Stars took on particular character during northern European sailings. Watching films under stars while sailing past the Norwegian coast — actual fjords visible beyond the screen's glow — added a dimension that Caribbean deployments cannot offer. The experience required warmer blankets and stronger resolve against occasional wind, but the atmospheric reward justified the minor thermal challenge.\n\nFor UK cruisers who've hesitated over logistics, Sky Princess from Southampton removes every barrier except the decision to book. Drive to port. Park. Walk aboard. Sail Europe. The simplicity transforms Princess from aspirational international brand to practical local option.\n\n**The lesson:** Experience teaches discernment — and what discernment teaches British cruisers is that world-class cruising no longer requires world-spanning travel to reach the gangway.",
      "author": {
        "name": "James and Catherine Howard",
        "location": "London, UK"
      }
    },
    {
      "title": "Movies Under the Stars: Why It Matters",
      "persona_label": "Signature Experience",
      "persona": "couples",
      "intended_reader": "Couples seeking romantic cruise experiences",
      "core_insight": "Sky Princess's Movies Under the Stars creates unique romantic opportunities",
      "markdown": "**Every Princess ship offers Movies Under the Stars. On Sky Princess, the experience achieves particular magic — and after twelve cruises across four lines, I can say with confidence that no other single amenity has produced more genuinely romantic moments for my wife and me than a massive screen, a shared blanket, and the stars above the Pacific.**\n\nThe concept sounds almost too simple to be significant. A large LED screen mounted above the pool deck. Films shown after sunset. Princess provides blankets and popcorn. Passengers arrange themselves on loungers and deck chairs. The technology is straightforward. The atmosphere is not.\n\nSomething happens when you watch a film at sea that cannot happen in any land-based cinema. The absence of phones — connectivity at sea remains limited enough that the reflexive screen-checking that ruins modern moviegoing simply doesn't occur. The impossibility of leaving early — where would you go that's better than this? The captive, voluntary attention creates shared focus between couples that land-based entertainment, with its infinite distractions, cannot replicate.\n\nSky Princess refined the venue with the advantage of being the newest Royal Class ship at her debut. The screen is optimized. The sound balances against ocean ambient noise rather than fighting it. The seating areas accommodate couples in configurations that feel intimate rather than crowded. The technical execution — invisible to passengers who simply show up and enjoy — represents years of refinement across the fleet.\n\nMy wife Sarah and I discovered Movies Under the Stars accidentally on our first Princess cruise six years ago. We'd finished dinner, found the pool deck transformed, and settled into a lounger with the blanket a crew member offered. The film was something we'd seen before — the familiarity didn't matter. What mattered was the specific quality of attention we gave each other during the film and after it. The way Sarah leaned against my shoulder as the plot developed. The whispered commentary that became our private conversation within a public space. The stars visible above the screen that the film's cinematographers couldn't compete with.\n\nThe ritual evolved across subsequent cruises into our defining couples activity. We'd plan our evenings around the film schedule. We'd claim our preferred lounger early. We'd order drinks from the bar and carry them to our spot. The preparation became part of the romance — the anticipatory pleasure of knowing that in thirty minutes, we'd be wrapped in a blanket together, anonymous among fellow passengers, sharing something beautiful.\n\nOn Sky Princess specifically, the Mediterranean deployment added atmospheric elements that Caribbean sailings handle differently. Warm evenings sailing past Italian coastline, the lights of villages visible beyond the pool deck. The scent of Mediterranean air mixing with popcorn. The specific romance of European waters viewed through the frame of an outdoor cinema — as though the ship had constructed the world's most elaborate date night setting and charged nothing for admission.\n\nThe Piazza provided our pre-movie gathering spot — drinks and conversation in the atrium's cafe atmosphere before walking to the pool deck for the evening's showing. The transition from social space to romantic space, from conversation to shared viewing, created a ritual with distinct movements: connection, then contemplation, then the walk back to our cabin under stars we'd been watching all evening.\n\nSarah tells people that Movies Under the Stars is her favourite thing about cruising. She's tried Crown Grill's exceptional steaks. She's experienced the Sanctuary's curated peace. She's walked the SeaWalk's transparent floor. She chooses the outdoor cinema — reliably, repeatedly, definitively. Not because it's the most impressive feature. Because it's the most romantic.\n\n**The lesson:** Romance doesn't require expensive gestures or elaborate planning — sometimes it requires only a blanket, a film, and the willingness to sit together under stars while the ocean carries you somewhere beautiful.",
      "author": {
        "name": "Andrew and Sarah Mitchell",
        "location": "Manchester, UK"
      }
    },
    {
      "title": "Our First Family Cruise Success",
      "persona_label": "Family Travel",
      "persona": "family",
      "intended_reader": "Families with children considering their first cruise",
      "core_insight": "Sky Princess provides excellent first-cruise experience for families with children",
      "markdown": "**Three kids under twelve. Two skeptical parents. One week on Sky Princess. The equation seemed designed for disaster, and the result surprised every one of us — including our eleven-year-old, who'd sworn on his skateboard that cruising was for old people and he'd hate every minute.**\n\nWe'd hesitated about cruising with children for years, armed with concerns that felt reasonable from our land-based perspective. Would a ship contain the kinetic energy of three children whose default setting operates between \"enthusiastic\" and \"demolition\"? Would the food work for palates that considered chicken nuggets and plain pasta the entirety of acceptable cuisine? Would the kids find enough to do between ports, or would we spend sea days managing boredom with the weary desperation of parents who've exhausted their entertainment arsenal?\n\nSky Princess answered every concern within the first twenty-four hours. Camp Discovery — Princess's kids' programme — absorbed our children with an enthusiasm I hadn't expected. Our six-year-old made friends before lunch on embarkation day. Our eight-year-old discovered arts activities that produced objects she actually wanted to keep rather than the usual holiday-programme debris. Our eleven-year-old — the sworn sceptic — found the teen activities engaging enough that he asked to go back after dinner on the first evening. He asked. Without prompting. The skateboard oath evaporated.\n\nThe MedallionClass technology served family logistics with particular effectiveness. We tracked the younger children's location through the app, which eliminated the specific parental anxiety of losing a six-year-old on a ship carrying over three thousand passengers. We could locate each other for meal times without the group text chaos that family vacations normally generate. The Medallion's touchless cabin entry meant no lost room keys — a genuine concern when your eight-year-old treats small objects as optional accessories.\n\nFood worked surprisingly well across three distinct palates and two distinct generations. The buffet offered enough variety that even our most dedicated nugget enthusiast found acceptable options. The pizza station — available throughout the day — served as the emergency backup that parents of young children require at all times. The main dining room accommodated our family seating with a waiter who learned within two evenings that our six-year-old needed bread immediately upon sitting, that our eight-year-old would try anything once but required a safety net of familiar alternatives, and that our eleven-year-old was ready to eat from the adult menu with the seriousness of someone auditioning for maturity.\n\nSea days surprised us most. We'd anticipated boredom. Instead, the pool deck occupied the children for hours — the kind of sustained aquatic engagement that home swimming pools never achieve because novelty wears off but cruise ship pools exist in a context of perpetual holiday that sustains interest. The Piazza provided our family gathering point when the pool eventually lost its grip. Ice cream appeared. A pianist played. Our children sat still long enough for us to drink coffee — a miracle that deserved its own celebration.\n\nPort days combined family adventure with ship-as-refuge. We'd explore European cities together — the energy of three children navigating cobblestone streets, the wonder on their faces at cathedrals and castles, the specific family joy of shared discovery. We'd return to the ship exhausted, and the children would head to the pool or Camp Discovery while we collapsed into loungers with the gratitude of parents who'd been granted unexpected reprieve.\n\nMovies Under the Stars became our family ritual — the activity all five of us chose without negotiation every single evening. Blankets spread across adjacent loungers. Popcorn distributed in proportions that reflected parental experience rather than democratic principle. Our eleven-year-old leaning against his mother in the darkness, a proximity he'd never have tolerated in daylight but accepted because the outdoor cinema's anonymity made family closeness permissible for a pre-teen. Even he admitted it was \"actually pretty cool.\"\n\nThe Sanctuary provided the couple time we hadn't dared hope for. While all three children attended programmes or played with newly made friends, we spent two afternoon hours in the adults-only retreat, lying on loungers, reading books, speaking in complete sentences — a luxury more precious than any suite upgrade.\n\n**The lesson:** Family cruising works when the ship provides enough for every age group to find genuine joy — and the families brave enough to try discover that the shared experience creates memories no theme park or beach resort can match.",
      "author": {
        "name": "The Thompson Family",
        "location": "Chicago, IL"
      }
    },
    {
      "title": "Solo Cruising Without Loneliness",
      "persona_label": "Solo Travel",
      "persona": "solo",
      "intended_reader": "Solo travelers considering Princess cruises",
      "core_insight": "Sky Princess welcomes solo cruisers with dignity and opportunity for connection",
      "markdown": "**I'd never cruised alone before Sky Princess. The decision came from necessity — my travel companion cancelled two weeks before departure, leaving me with a non-refundable booking and the choice between losing the fare or boarding alone. I boarded alone. And the experience taught me that solo cruising can be more liberating than any trip I'd taken with company.**\n\nThe concerns that accompanied me up the gangway were predictable and powerful. Would dining alone feel conspicuous in a room designed for couples and families? Would I spend every evening as the visible exception to an unspoken rule about travelling in pairs? Would the ship's social architecture exclude a woman travelling solo at forty-seven, or worse, would it pity her?\n\nSky Princess addressed these worries with a naturalness that suggested experience rather than policy. The dining room staff seated me efficiently and thoughtfully — sometimes with interesting tablemates who enriched my evenings with conversation I'd never have found travelling with a companion whose presence precluded new connections. A retired journalist from Edinburgh who told stories about covering elections in impossible places. A couple from Toronto who'd sailed twenty Princess voyages and treated me as their dinner companion with the ease of people who'd been hosting guests their entire lives. And sometimes the staff seated me at comfortable tables for one, where I ate with a book propped against my water glass and felt not lonely but luxuriously self-contained.\n\nMedallionClass technology transformed solo navigation from anxious to autonomous. The app showed me where every venue was, what was happening when, how to reach anything from anywhere. No asking strangers for directions while feeling conspicuously unaccompanied. No fumbling with deck plans in busy corridors. The Medallion opened my cabin door as I approached — a convenience that felt disproportionately significant when there was no companion to hold the bags while I searched for a key.\n\nThe ship's size provided exactly the balance solo travel requires: anonymity when I wanted invisibility, community when I wanted connection. I could disappear into a book at the Sanctuary for an entire afternoon without anyone wondering where I was or whether I was okay. I could join trivia in the lounge and find myself absorbed into a team of strangers who needed a fourth and didn't care that I'd arrived alone. The choice remained mine at every moment — the fundamental requirement of solo travel that group-oriented vacations sometimes violate.\n\nThe Piazza became my social anchor. That central atrium functioned as a village square where I could sit with coffee, observe the ship's daily life, and choose my level of participation moment by moment. Some mornings I watched quietly. Some afternoons I joined conversations that formed naturally around the bar. The space allowed transitions between solitude and sociability without either feeling forced.\n\nShore excursions mixed group and solo options in proportions I could calibrate daily. I joined a guided tour of Dubrovnik where shared enthusiasm for the architecture generated easy conversation. I wandered Barcelona's Gothic Quarter alone, following streets that looked interesting without negotiating with anyone about pace or direction. The freedom to choose daily between company and independence defined my vacation's rhythm.\n\nMovies Under the Stars became my evening constant. Wrapped in a blanket, anonymous in pool-deck darkness, watching films while the ship sailed Mediterranean waters. The communal solitude suited my state perfectly — together with hundreds of passengers without obligation to any of them. Connected through shared attention without shared conversation. The experience captured what solo cruising offers at its best: belonging without attachment.\n\nPrincess's demographic suited my solo experience well. Passengers skewed mature and mellower than the party-focused lines I'd researched and rejected. Conversations happened organically in lounges and on deck — the kind of natural social interaction that doesn't require ice-breakers or structured mixers. People talked because they wanted to, not because activities forced them together.\n\n**The lesson:** Solitude doesn't have to mean isolation — and the ship that treats solo travelers as guests rather than anomalies reveals that travelling alone can be the most freeing kind of travel there is.",
      "author": {
        "name": "Jennifer Collins",
        "location": "Seattle, WA"
      }
    },
    {
      "title": "Our Honeymoon Aboard Sky Princess",
      "persona_label": "Honeymoon",
      "persona": "honeymoon",
      "intended_reader": "Newlyweds planning honeymoon cruises",
      "core_insight": "Sky Princess provides romantic atmosphere perfect for honeymoons",
      "markdown": "**We chose Sky Princess for our honeymoon because we wanted romance without isolation — celebration and adventure woven together across a week that would set the tone for our marriage. The ship delivered both so seamlessly that we stopped trying to distinguish between the romantic moments and the adventurous ones. They were the same thing.**\n\nThe honeymoon planning had exhausted us nearly as thoroughly as the wedding. Beach resort: romantic but potentially claustrophobic after three days of sand and each other's uninterrupted company. European tour: exciting but logistically demanding after months of wedding stress that had left us both craving simplicity. A Mediterranean cruise emerged from our travel agent's suggestion as the resolution: daily variety, built-in romance, adventure available at every port, and the option to do absolutely nothing whenever nothing felt like the most romantic choice.\n\nOur balcony stateroom became our first private retreat as a married couple — the space where we discovered what married mornings actually feel like versus dating mornings. Morning coffee watching Greek islands emerge from Mediterranean haze. Evening champagne as the ship navigated between ports whose names we were still learning to pronounce. Room service breakfasts where I discovered that my wife, who'd seemed perfectly put-together throughout our courtship, considers pre-9 AM conversation a form of assault. The balcony provided intimate moments within a shared journey — small enough for whispered conversations, large enough for companionable silence.\n\nThe Sanctuary adults-only retreat earned its supplemental fee within the first hour. Reserved loungers overlooking the ocean. Attentive service that appeared without being summoned. The specific quality of peace that honeymoons require and cruise ships don't always achieve. We lay there reading, talking, learning the rhythms of married silence — which differs from dating silence in ways I'm still understanding. The Sanctuary created a pocket of calm within a ship of three thousand passengers where we could be alone together without being alone.\n\nSabatini's Italian restaurant provided our most memorable dinner. The white linens. The candlelight. Pasta prepared with a generosity that felt Italian rather than institutional. Our waiter, learning we were honeymooning, treated the evening as though our celebration deserved his personal investment. He recommended dishes with the enthusiasm of someone sharing family recipes rather than reciting a menu. The tiramisu he suggested for dessert arrived with the quiet confidence of a final course that knew it would seal the evening perfectly.\n\nCrown Grill offered the complement — a steakhouse evening where excellence took a different form. Precision rather than warmth. Technical mastery rather than Italian abundance. Both restaurants honored our honeymoon without making it a performance. The crew acknowledged our newlywed status and then respected our preference for celebrating privately rather than publicly.\n\nThe SeaWalk provided our most photographed moment. Standing together on the glass floor extending over the ocean, 128 feet above the Mediterranean, holding hands because the transparency beneath our feet demanded trust. Emma's expression — delight crossed with vertigo — became the image we framed for our first apartment. The SeaWalk captured our honeymoon's philosophy: adventure and trust, shared simultaneously.\n\nPort days added cultural discovery to romantic itinerary. Exploring Barcelona's Gothic Quarter hand in hand. Getting lost in Dubrovnik's medieval streets and finding a cafe where the owner poured us wedding-congratulations rakia. Watching sunset from Santorini's caldera while our ship waited in the harbour below. Each port offered a different setting for the same ongoing conversation: who are we as married people, and what kind of life are we building?\n\nMovies Under the Stars sealed our nightly ritual. One blanket. One lounger. Stars above the screen, the Mediterranean below the ship, and the specific sweetness of falling asleep against someone you've just promised your life to while a film plays softly overhead.\n\n**The lesson:** The best honeymoon teaches partnership through both joy and challenge — and the ship that makes every evening feel like a different kind of celebration gives newlyweds the variety their new marriage needs to discover itself.",
      "author": {
        "name": "Michael and Emma Richardson",
        "location": "Toronto, Canada"
      }
    },
    {
      "title": "Cruising at 82: Still Wonderful",
      "persona_label": "Senior Travel",
      "persona": "elderly",
      "intended_reader": "Travelers in their 70s and 80s considering cruise options",
      "core_insight": "Sky Princess accommodates elderly travelers with appropriate amenities and pacing",
      "markdown": "**At eighty-two, I wondered if cruising remained practical for a man whose knees file daily grievances, whose hearing requires strategic seating, and whose energy reserves deplete by mid-afternoon with the reliability of a clock. Sky Princess proved that practical and wonderful can coexist — the ship doesn't just accommodate age; she respects it.**\n\nThe concerns that keep elderly travelers at home are specific, practical, and rarely addressed by cruise marketing that features sprightly seventy-year-olds jogging on deck at sunrise. Can I manage the walking distances between dining room and cabin when my legs inform me at 6 PM that they've fulfilled their daily contract? Will elevators appear when gravity and fatigue conspire against the staircase option? Will the pace of activities exhaust me by noon, leaving the afternoon and evening offerings inaccessible? Will staff see a guest worth serving or a complication worth managing?\n\nSky Princess addressed every worry with the Royal Class thoroughness I'd come to expect from Princess after nine previous voyages across two decades. The ship's layout made navigational sense — elevators positioned where logic and tired legs agreed they should be. Corridors wide enough for my occasionally uncertain gait without the embarrassment of blocking foot traffic. The distance between my cabin and the main dining room measured six comfortable minutes. The distance between the dining room and the theater measured four. These measurements matter enormously at eighty-two, because they determine whether an evening includes dinner and a show or forces a choice between them.\n\nThe MedallionClass technology proved unexpectedly helpful. I'd resisted technology throughout my retirement — my children can attest to my principled objection to anything requiring passwords or updates. But the Medallion demanded nothing except wearing it. My cabin door opened as I approached. No fumbling with cards that arthritic fingers struggle to grip. No remembering which pocket held the key when seven pockets compete for attention. The technology removed daily friction that younger passengers might not notice but that accumulates into genuine frustration when multiplied across a week of repeated encounters.\n\nDining accommodated my pace without any suggestion that my pace represented a problem. My waiter observed that I needed a moment to settle into my chair before considering menus. He learned my dietary requirements within two evenings — the sodium restriction, the medication schedule that demanded eating at precise intervals, the lactose sensitivity that had developed in my late seventies. These needs, managed without nightly re-negotiation, transformed dining from medical logistics into genuine pleasure.\n\nThe passenger demographic included substantial numbers of mature travelers — fellow octogenarians, septuagenarians, retired couples who understood that a good evening means a show that ends by nine followed by quiet reading. Conversations at dinner carried the weight that decades provide. We discussed books and grandchildren and the particular satisfaction of having survived enough to know which worries deserve energy and which deserve dismissal.\n\nThe Sanctuary provided daily refuge without requiring justification. That adults-only retreat normalized rest — other passengers dozed openly, read slowly, sat in sunshine without apologizing for inactivity. The permission to simply exist felt genuinely restorative for someone whose home life sometimes carries the faint implication that rest equals decline.\n\nMovies Under the Stars accommodated my preferences perfectly — comfortable outdoor seating, reasonable volume, the option to leave whenever fatigue arrived without navigating dark theater aisles. I fell asleep during two films. My wife covered me with an extra blanket and watched the endings alone. Neither of us considered this a failure. At eighty-two, falling asleep during a movie under the stars while your wife watches over you feels less like surrender and more like trust.\n\nThe medical facilities provided the peace of mind that allows genuine relaxation. The ship's doctor reviewed my medications professionally, provided guidance specific to cruising conditions, and offered the reassurance that competent help existed within minutes of any location aboard.\n\n**The lesson:** Age is irrelevant when service means respect — and the ships that welcome elderly travelers as honoured guests rather than logistical challenges earn the kind of loyalty that lasts as long as we do.",
      "author": {
        "name": "Harold Stevens",
        "location": "Phoenix, AZ"
      }
    },
    {
      "title": "Traveling After Loss",
      "persona_label": "Widow Travel",
      "persona": "widow",
      "intended_reader": "Widows and widowers considering travel after losing a spouse",
      "core_insight": "Sky Princess provides supportive environment for those traveling after losing partners",
      "markdown": "**My wife and I cruised Princess for twenty-three years — eleven voyages, always the same line, always the same sense of coming home to a ship that knew us. After she passed, I assumed cruising was finished. Then my daughter booked Sky Princess and said: 'Dad, Mom would kill you if you stopped sailing.' She was right. Katherine would have been furious.**\n\nKatherine had been the cruise planner. She researched itineraries with the methodical joy of someone who understood that anticipation is part of the gift. She chose cabins based on criteria I never fully grasped — something about deck level and proximity to elevators that reflected an understanding of ship design I'd never developed because I'd never needed to. She handled everything. I showed up, unpacked, and followed her to dinner. Twenty-three years of that partnership had produced eleven perfect voyages and zero independent travel skills.\n\nThe first cruise alone felt terrifying in ways I hadn't anticipated. Embarkation without Katherine required decisions I'd never made. Which line to join. Where to put the luggage. How to find the cabin. The MedallionClass technology helped — the Medallion opened my door without the card-fumbling that Katherine had always handled — but the technology couldn't replace the person who'd navigated every voyage beside me.\n\nDinner tested every particle of courage I possessed. The table set for couples. The empty chair across from me that should have held Katherine, who'd have been studying the menu with the focus she brought to everything. The wine list she'd have scrutinized and from which she'd have selected something I'd never have chosen myself but would have loved because she had impeccable taste and I had impeccable trust. I ordered her favourite wine — a New Zealand sauvignon blanc she'd discovered on our eighth voyage — and drank it alone.\n\nBut Sky Princess offered gentle reentry. Crew members' warmth filled spaces that grief had hollowed without trying to fill the specific space Katherine had occupied. My cabin steward left thoughtful touches that communicated care — fresh flowers, a note hoping I was enjoying the voyage. The dining staff seated me with couples who included me naturally, without the awkward pause that sometimes accompanies the arrival of a solo diner at a table designed for even numbers.\n\nThe ship held space for both grief and beauty simultaneously. Sunset from the balcony brought tears and wonder in equal measure — the Mediterranean sky performing its nightly transformation while I watched alone from a chair that used to hold Katherine's book and reading glasses. The Piazza's pianist played songs she'd hummed along with, and I found myself humming in her place. The observation deck offered the contemplative hours that grief requires — watching ocean pass, feeling the specific ache of beauty witnessed without the person who'd have described it better than I could.\n\nI found other widowers aboard, naturally, the way those who've lost partners recognise each other across dining rooms and observation decks. A retired teacher from Bristol. A former architect from Glasgow. We shared meals and excursions and the particular communion of men who'd loved well and lost completely. The conversations required no explanation. We understood each other's silences as fluently as our words.\n\nMovies Under the Stars became my evening anchor — the darkness providing anonymity, the film providing focus, the blanket providing the warmth that my empty cabin couldn't. Katherine had loved Movies Under the Stars. Watching films without her hurt. Not watching them would have hurt more.\n\nBy voyage end, something had shifted. Not resolution — grief doesn't resolve on a ten-day sailing. But movement. I'd proven I could navigate the world Katherine had always navigated for me. I could order wine and find my cabin and eat dinner alone and survive. Katherine would have been proud. She also would have critiqued my wine selection.\n\n**The lesson:** Grief needs beautiful places to breathe — and returning to the ships you loved together is its own form of honouring the one who loved them first.",
      "author": {
        "name": "Robert Harrison",
        "location": "Tampa, FL"
      }
    },
    {
      "title": "Cruising with My Wheelchair",
      "persona_label": "Accessible Travel",
      "persona": "accessible",
      "intended_reader": "Travelers with mobility limitations considering cruises",
      "core_insight": "Sky Princess provides comprehensive accessibility features for wheelchair users",
      "markdown": "**My wheelchair doesn't prevent cruising — it just sharpens my criteria for choosing a ship. After nine cruises across five lines, I've learned that the gap between marketed accessibility and actual accessibility can be measured in bruised shins and lost dignity. Sky Princess narrowed that gap more effectively than any ship I've sailed, and the Royal Class infrastructure deserves specific credit.**\n\nAccessibility on cruise ships exists along a spectrum invisible to walking passengers. At one end: ships that checked legal compliance boxes during construction and consider accessibility addressed. At the other end: ships where someone who actually uses a wheelchair influenced decisions about threshold heights, turning radii, and the positioning of grab bars relative to actual transfer points. Sky Princess falls closer to the latter — not perfect, but genuinely thoughtful in ways that matter daily.\n\nThe accessible cabin exceeded standard compliance. The roll-in shower worked — properly worked, with grab bars positioned where physics and human anatomy agree they should be, not where an engineer's diagram met minimum code without consulting someone who transfers from a wheelchair to a shower bench multiple times daily. The turning radius accommodated my power chair without the furniture rearrangement that some ships require. The balcony threshold — consistently the most common accessibility failure I encounter — allowed my chair to cross independently. That single design detail, which walking passengers never notice, determined whether my cabin included outdoor space or merely promised it.\n\nPublic spaces accommodated my chair with the consistency that Royal Class infrastructure enables. Elevators appeared where logic positioned them and operated with capacity sufficient for peak-hour demand. I tracked my wait times across the voyage: the longest was four minutes. For wheelchair users, every minute waiting for an elevator is a minute of independence lost and a minute of visible dependency gained. Sky Princess kept those minutes minimal.\n\nThe MedallionClass technology provided accessibility benefits that may not have been explicitly designed for wheelchair users but that we gratefully discover. Touchless cabin entry eliminated the fumble — hands occupied with wheel rims or joystick controls cannot simultaneously extract and position a keycard. The Medallion sensed my approach and opened the door. The independence this preserved was disproportionate to the technology's apparent simplicity.\n\nTheater seating positioned my wheelchair where sightlines actually worked — integrated into the audience rather than relegated to corners where accessible means invisible. The dining room accommodated my chair by removing a standard chair and creating appropriate spacing before I arrived, adjustments choreographed invisibly enough that my dinner companions didn't notice the preparations.\n\nShore excursions required the careful selection that wheelchair users accept as standard. Not every European port accommodates wheelchairs genuinely. Cobblestones defeat most mobility devices. Medieval cities weren't designed for wheels. But Sky Princess's excursion staff provided honest guidance — distinguishing tours that work for wheelchairs from tours that claim to work but involve optimistic reassurances about \"just a few steps.\" The honesty saved me from disappointments I'd experienced on other ships.\n\nCrown Grill demonstrated accessible fine dining at its best. Appropriate spacing. Server approach from my accessible side. No waiting at the entrance while staff improvised solutions. The steak was exceptional. The invisible accommodation made it comfortable enough to truly enjoy rather than merely endure.\n\nThe SeaWalk accommodated my wheelchair, providing the same glass-floor, ocean-below perspective that walking passengers experienced. Staring down through transparent floor at the Mediterranean 128 feet below, my disability irrelevant to the vertigo, I felt exactly what everyone else felt: wonder.\n\n**The lesson:** Accessibility means equal dignity, not special treatment — and the ships that understand the difference between compliance and genuine inclusion earn a loyalty wheelchair users carry aboard every voyage.",
      "author": {
        "name": "Catherine Williams",
        "location": "Denver, CO"
      }
    },
    {
      "title": "Mediterranean Magic",
      "persona_label": "Regional Focus",
      "persona": "adventure",
      "intended_reader": "Travelers planning Mediterranean cruises",
      "core_insight": "Sky Princess excels in Mediterranean deployment with optimized itineraries",
      "markdown": "**Sky Princess sails the Mediterranean regularly, and after experiencing the combination of Royal Class refinement with Mediterranean destinations, I understood why some ships and some seas create partnerships so natural they feel designed by the same architect. The Mediterranean was made for cruising. Sky Princess was made for the Mediterranean.**\n\nThe argument for Mediterranean cruising requires no salesmanship. The region concentrates more history, culture, cuisine, and beauty per nautical mile than any other body of water ships navigate. The challenge isn't finding compelling destinations — they're everywhere — but experiencing them without the logistical exhaustion that Mediterranean land travel sometimes produces. Flights between cities. Hotel check-ins. Language transitions. Currency changes in some ports. A cruise eliminates the connective tissue between destinations and presents only the destinations themselves.\n\nSky Princess suits the Mediterranean with particular effectiveness. The Piazza atrium — that signature Princess social space — echoes the Italian piazzas that inspired its design more authentically when the ship is actually sailing Italian waters. The outdoor spaces thrive in Mediterranean warmth. The SeaWalk's glass-bottomed walkway, extending over water that shifts from Adriatic blue to Aegean turquoise to Tyrrhenian deep, provides perspectives that change character with every sea the ship navigates.\n\nThe itineraries from Southampton and Barcelona reach diversity that no land-based vacation could replicate in equivalent time. Barcelona's Gaudi architecture. Rome's layered history, accessible through Civitavecchia. The Greek islands — Santorini's white villages against volcanic cliffs, Mykonos's windmills, the ancient ruins that islands smaller than city parks somehow contain. Dubrovnik's medieval walls. The Amalfi Coast's impossible road carved into cliff faces. Each port delivered a different chapter of Mediterranean civilization, and the ship carried us between chapters while we rested, ate, and processed what we'd seen.\n\nMedallionClass technology worked seamlessly across European port operations. The Medallion identified us at every re-boarding, streamlining the security process that busy Mediterranean ports can make tedious. The app provided port information, excursion meeting points, and ship departure times with the accessibility that prevents the most common Mediterranean cruising anxiety: missing the ship.\n\nDining reflected regional influences with appropriate subtlety. Mediterranean flavors appeared in the main dining room's rotating menus — fresh seafood prepared with olive oil and lemon, pasta that honoured its Italian origins, salads that tasted like the sun-warmed ingredients they contained. Crown Grill served Mediterranean-sourced ingredients alongside its standard premium menu. Sabatini's Italian restaurant felt less like a theme and more like authentication when the ship was literally sailing the waters that inspired the cuisine.\n\nSea days between ports provided essential recovery. Mediterranean cruising's density of experience can exhaust without respite — too many cathedrals, too many museums, too many cobblestoned hills in too few days. Sky Princess offered the counterpoint: pools, loungers, the Sanctuary's curated peace, the observation deck where I could watch the sea that connected every civilization we'd visited and feel the continuity that land travel breaks into disconnected segments.\n\nMovies Under the Stars achieved particular beauty during Mediterranean evenings. Warm air. Clear skies. Italian coastline visible beyond the pool deck. The outdoor cinema's screen competed with the scenery and wisely didn't try too hard — the film provided foreground entertainment while the Mediterranean provided context that no cinematographer could match.\n\nThe passenger mix on Mediterranean sailings tends international — Americans, British, Europeans, Australians converging on shared fascination with the region. The cosmopolitan atmosphere at dinner reflected the destinations the ship visited: conversations that crossed cultures with the ease of people who'd chosen the same beautiful waters.\n\n**The lesson:** The best cruise destinations don't need selling — they need the right ship to reveal them, and Sky Princess's Royal Class elegance meets the Mediterranean's timeless beauty with the mutual respect of equals.",
      "author": {
        "name": "The Anderson Family",
        "location": "Boston, MA"
      }
    },
    {
      "title": "First Cruise on a Modern Ship",
      "persona_label": "First Cruise Experience",
      "persona": "first-timer",
      "intended_reader": "First-time cruisers attracted to newer ships",
      "core_insight": "Sky Princess makes first-time cruising intuitive through MedallionClass technology and refined design",
      "markdown": "**I'd avoided cruising for years, convinced the experience would involve getting lost in labyrinthine corridors, eating in cavernous dining halls where everyone knew the etiquette except me, and missing the ship in some foreign port while I stood on a dock watching it sail away with my luggage. Then friends suggested Sky Princess, promising the technology would make everything simple. They were right — and the simplicity changed everything.**\n\nMy cruise anxieties had been curated over a decade of avoidance. Getting lost on a ship large enough to carry a small town's population. Missing announcements about dinner seatings or lifeboat drills or port arrivals. Fumbling with room keys in front of experienced cruisers who'd glide through the process with the casual expertise that makes beginners feel like imposters. Standing alone in a massive atrium, overwhelmed by choices, directions, and the accumulated confidence of three thousand passengers who all seemed to know exactly where they were going.\n\nMedallionClass technology eliminated every concern with an efficiency that felt almost unfairly simple. The Medallion — a small wearable disc — replaced the traditional cruise card. It opened my cabin door as I approached. No fumbling. No searching pockets. No standing in the corridor performing a one-person comedy about lost keys while a queue formed behind me. The app on my phone showed me where to go, what was happening when, where my friends were exploring, how to reach any location from wherever I stood. Navigation became intuitive within hours of boarding.\n\nThe Piazza provided my orientation anchor — the central atrium where everything made sense. That space felt like a familiar cafe: comfortable seating, excellent coffee, natural light streaming through the multi-deck glass ceiling, a pianist playing something that encouraged lingering. Whenever the ship felt too large or my confidence too small, I returned to the Piazza. From there, everything else was reachable by simple directions the app provided. The Piazza became my home base, and every exploration started and ended there until the entire ship felt familiar.\n\nDining worked better than any first-timer scenario I'd dreaded. I'd imagined rigid protocols — formal dress codes enforced by disapproving staff, mysterious courses arriving in sequences I'd navigate incorrectly, wine selection procedures that would expose my ignorance to an entire dining room. Instead, I found flexibility and warmth. The main dining room offered formal elegance when I wanted it and casual alternatives when I didn't. The staff treated first-timers as exciting arrivals rather than inconvenient interruptions.\n\nCrown Grill provided my most surprising dining experience — a specialty steakhouse where the sommelier asked about my preferences with genuine curiosity and recommended a wine that taught me something about my own palate. The meal exceeded any steakhouse I'd visited at home. Sabatini's Italian restaurant offered warm generosity that made formal dining feel like a family dinner at an Italian grandmother's table.\n\nThe SeaWalk provided the experiential highlight — standing on the glass-bottomed walkway extending over the ocean, 128 feet above the Mediterranean, feeling the specific thrill of transparency beneath my feet. No amount of pre-cruise research had prepared me for the visceral reality of glass floor and infinite depth. The experience belonged to the category of things that must be felt rather than described.\n\nMovies Under the Stars clinched my conversion on the third evening. Wrapped in a blanket on the pool deck, watching a film under actual stars, the Mediterranean providing gentle motion beneath me. The experience required nothing — no skills, no knowledge, no expertise. Just presence. Just willingness. Just showing up and letting the ship create something beautiful.\n\nSky Princess converted a committed sceptic in seven days. My second cruise was booked before disembarkation.\n\n**The lesson:** Modern technology can make classic experiences more accessible, not less authentic — and the ship that removes every barrier to entry gives first-timers permission to discover what experienced cruisers already know.",
      "author": {
        "name": "Amanda Richardson",
        "location": "Nashville, TN"
      }
    },
    {
      "title": "Three Sisters Turn Sixty",
      "persona_label": "Milestone Birthday",
      "persona": "special-occasion",
      "intended_reader": "Siblings celebrating shared milestones together",
      "core_insight": "Sky Princess creates space for sibling milestones that honor shared history",
      "markdown": "**My sisters and I turned sixty within eighteen months of each other. We'd always celebrated together — every birthday, every milestone, every victory and heartbreak compressed into a sisterhood that spans our entire lives. This birthday deserved more than dinner at the usual restaurant. Sky Princess gave us the celebration our sisterhood had earned over six decades of sharing everything.**\n\nThe triple-sixty had been approaching with the inevitability that milestone birthdays carry — not just the number but the reckoning it demands. Sixty years of being sisters. Sixty years of shared bedrooms and borrowed clothes and whispered confidences and screaming arguments that resolved within hours because sisterhood doesn't allow prolonged silences. We'd navigated each other's weddings, divorces, children, career changes, and the slow transformation of our parents from authority figures to people who needed us more than we needed them. Sixty deserved acknowledgement. Sixty deserved a cruise.\n\nOur cabins occupied the same deck — a detail we'd specifically requested and Sky Princess specifically honoured. The proximity recreated something from childhood: doors open between rooms, voices carrying through walls, the ability to wander between spaces without ceremony. Morning coffee happened on adjoining balconies, three mugs, three sisters, three variations on the same face watching the same Mediterranean sunrise. The view had improved since the three of us shared a bedroom overlooking a parking lot in suburban Boston.\n\nThe crew learned about our celebration naturally — three women of nearly identical age occupying three adjacent cabins generate curiosity — and their response exceeded any expectation we'd carried aboard. Our cabin steward coordinated daily: different flowers for each sister, reflecting preferences he'd somehow determined without asking. The dining room staff learned which sister preferred wine, which drank sparkling water, which always wanted extra dessert. They remembered without notes, and the remembering felt like recognition rather than service.\n\nBirthday cakes arrived at three different dinners — each personalized with details we'd shared during conversations the staff had apparently been paying closer attention to than we'd realised. My cake referenced my teaching career. Susan's referenced her garden. Patricia's referenced her grandchildren. The specificity proved someone had listened and cared enough to translate listening into action.\n\nThe Sanctuary became our sisterhood space — three loungers together, hours of conversation about our childhood, our marriages, our children, our losses, our futures. The conversations we'd been promising ourselves for years — the deep ones, the honest ones, the ones that require uninterrupted hours and the safety of a space where nobody judges — finally happened with Mediterranean sun warming our faces and attendants bringing water without disturbing the flow of stories that spanned our entire lives.\n\nMovies Under the Stars became our evening ritual — three blankets, one lounger each, popcorn shared across armrests with the familiar choreography of women who've been sharing snacks since grade school. We whispered commentary through every film, the same habit that had gotten us thrown out of a movie theater when we were fourteen, twelve, and eleven. Nobody threw us out on Sky Princess. The darkness accommodated our whispers.\n\nCrown Grill provided our birthday dinner venue — three sisters at a table meant for celebration, steaks ordered with the decisiveness of women who've earned the right to know exactly what they want. The sommelier selected a wine that honoured the occasion with appropriate weight. We lingered for hours, nobody rushing us, the restaurant holding our celebration with patience.\n\nPhotos from that voyage now hang in three homes across three states. Not professional portraits but candid shots: three sisters laughing at the rail, three sisters holding hands during sunset, three sisters toasting sixty years with champagne that tasted exactly like shared history should.\n\n**The lesson:** Sibling bonds deserve celebration that honours the lifetime of connection behind them — and the ships that recognise milestone birthdays as family history rather than calendar events create the space where sixty years of sisterhood finally gets the ceremony it always deserved.",
      "author": {
        "name": "The Morrison Sisters",
        "location": "Boston, MA; Chicago, IL; Austin, TX"
      }
    },
    {
      "title": "Finding Purpose After Retirement",
      "persona_label": "Recovery Journey",
      "persona": "healing",
      "intended_reader": "Those struggling with identity after major life transitions",
      "core_insight": "Sky Princess provides space for those rediscovering who they are beyond former roles",
      "markdown": "**Retirement hit harder than any surgery I'd performed in forty years. After four decades as a cardiac surgeon — a profession that defines you so completely that your name becomes your title — I didn't know who I was without a scalpel in my hand. Sky Princess became part of the painful, necessary process of remembering that I existed before I became Dr. Williams, and would need to exist after.**\n\nMedicine had been everything: identity, purpose, community, daily structure, the reason I woke before dawn and the reason I fell asleep exhausted. Retirement removed all of it simultaneously, the way a surgeon removes a tumor — necessary but traumatic, the wound requiring healing that the procedure itself cannot provide. The freedom everyone congratulated me for felt more like emptiness. My wife suggested cruising. I had no better ideas and no energy to generate alternatives.\n\nSky Princess asked nothing of me professionally. This gift — the absence of demand — proved harder to accept than the most complex surgery I'd ever attempted. No one aboard needed my expertise. No one looked to me for life-and-death decisions. No nurse called my name with urgent authority. No patient depended on my hands remaining steady. The relief and the terror arrived simultaneously, which is apparently what happens when you remove the load-bearing wall from a forty-year structure.\n\nI spent mornings on the observation deck, watching the Mediterranean pass, thinking about who I was without the title. The question had no obvious answer. I'd merged self with profession so completely that separating them required work I hadn't anticipated — like removing adhesions from tissue that had grown together over decades. The surgical metaphor came automatically. Everything came back to surgery. That was the problem.\n\nThe MedallionClass technology intrigued my analytical mind in ways that surprised me. I found myself studying how the systems worked — the Medallion's proximity sensing, the app's location services, the coordination platform that kept three thousand passengers navigating smoothly. I asked crew members technical questions about the engineering. Their willingness to explain — and my genuine interest in understanding — demonstrated something I'd feared retirement had killed: curiosity. The curiosity that had driven me into medicine forty years ago still existed. It simply needed new subjects.\n\nCrown Grill's precision reminded me that excellence exists across all professions. The chef's knife work, the sommelier's expertise, the dining team's coordination — all displayed mastery that paralleled surgical standards in different material. Excellence is transferable. The recognition comforted a man who'd assumed his particular form of excellence was the only one that mattered.\n\nFellow passengers included other retired professionals navigating similar disorientation. A former federal judge who missed the bench. A retired CEO who kept reaching for a phone that no longer rang with decisions requiring her authority. An ex-airline pilot who still dreamed about cockpit procedures. We found each other at dinner, drawn together by the shared bewilderment of lives that had been defined by purpose now searching for new definitions. Our conversations helped in ways our families' encouragement couldn't — not because our families lacked understanding, but because they'd never lost an identity the way professionals lose theirs at retirement.\n\nThe Sanctuary offered contemplative space where identity questions could breathe without resolution pressure. Lying on a lounger, watching clouds move across Mediterranean sky, I practiced being no one in particular. The practice was uncomfortable and necessary. Identity reconstruction doesn't happen in a week. But it begins when you stop performing the old role and start sitting with the emptiness.\n\nBy voyage end, I hadn't solved retirement. But Sky Princess had given me a week of practicing existence without professional purpose. The horizon kept expanding regardless of my credentials. Beauty didn't require my expertise to be beautiful. The ocean didn't care that I'd saved lives. It stretched endlessly, indifferent to my accomplishments, and in that indifference I found the beginning of freedom.\n\n**The lesson:** We are more than our professional identities — but discovering that more requires deliberate practice, and the ships that ask nothing of us give us space to discover who we are when we stop being what we did.",
      "author": {
        "name": "Dr. Robert Williams (Ret.)",
        "location": "Minneapolis, MN"
      }
    }
  ]
}