{
  "ship": "Sun Princess",
  "ship_class": "Sphere Class",
  "cruise_line": "Princess Cruises",
  "last_updated": "2026-01-21",
  "content_protocol": "ICP-Lite v1.4",
  "stories": [
    {
      "title": "The Sphere Revolution: Princess Enters a New Era",
      "persona_label": "Design Innovation",
      "persona": "heritage",
      "intended_reader": "Long-time Princess cruisers evaluating the new Sphere Class",
      "core_insight": "Sun Princess introduces the revolutionary Sphere atrium, Princess Cruises' first entirely new ship class in a decade",
      "markdown": "**Sun Princess launched in 2024 as the first Sphere Class ship\u2014Princess Cruises' first completely new ship class since the Royal Class debuted with [Royal Princess](/ships/princess/royal-princess.html) in 2013.**\n\nA decade is an eternity in the cruise industry. While Princess refined the Royal Class through six iterations, competitors launched revolutionary vessels. Norwegian built Breakaway. Royal Caribbean introduced Quantum. Celebrity premiered Edge. Princess perfected what existed rather than reimagining the future.\n\nSun Princess changes everything. The three-deck Sphere atrium represents architectural ambition unprecedented in Princess history. Previous ships featured the elegant Piazza\u2014a refined Italian plaza. The Sphere takes that gathering concept vertical, creating a soaring glass-enclosed entertainment venue that transforms throughout the day.\n\nDuring daylight, the Sphere functions as an elegant lounge where natural light floods through floor-to-ceiling glass. As evening arrives, it becomes an immersive theater with wraparound LED screens presenting productions that use the entire three-story space. Dining, entertainment, and social gathering happen simultaneously in overlapping zones.\n\nAt 175,500 gross tons carrying 4,300 guests, Sun Princess also represents Princess embracing mega-ship scale. She's substantially larger than any previous Princess vessel. Yet the Princess DNA persists\u2014refined service, MedallionClass technology elevated to new capabilities, and the signature Movies Under the Stars experience preserved.\n\nFor Princess veterans, Sun Princess poses a question: is this still the Princess you love, or has the line evolved beyond recognition? The answer matters for your next booking decision. [Star Princess](/ships/princess/star-princess.html) follows as the second Sphere Class ship, so this represents Princess's future, not an experiment.",
      "author": {
        "name": "Captain Michael Torres (Ret.)",
        "location": "Fort Lauderdale, FL"
      }
    },
    {
      "title": "Our First Mega-Ship Cruise: Why We Chose Sun Over Royal Caribbean",
      "persona_label": "Family Decision",
      "persona": "family",
      "intended_reader": "Families comparing mega-ships across cruise lines",
      "core_insight": "Sun Princess offers mega-ship scale with Princess's refined service style",
      "markdown": "**We'd cruised Princess on mid-sized ships before. Icon of the Seas dominated our kids' social media feeds. But we chose Sun Princess for our family's first mega-ship experience\u2014here's why.**\n\nThe decision came down to culture. Icon promises neighborhood concepts, waterparks, and endless stimulation. Sun Princess offers similar scale\u20144,300 guests rivals Icon's 5,600\u2014but maintains Princess's more refined atmosphere. Our teenagers wanted excitement. My husband and I wanted sanity. Sun Princess promised both.\n\nThe Sphere delivered the wow factor our kids craved. They watched immersive shows with 270-degree screens and acrobatic performers. They posted photos that impressed their friends. Meanwhile, we appreciated that the entertainment felt elegant rather than frenetic.\n\nMedallionClass technology proved essential for family coordination. Our teenagers could explore independently while we tracked their location. They ordered food and drinks charged to our account. They checked into activities without paperwork. The freedom kept them happy. The oversight kept us calm.\n\nDining worked beautifully for our multi-generational group. Grandparents preferred the traditional main dining room with formal service. Our kids wanted Alfredo's pizza and burgers at odd hours. Specialty restaurants satisfied adventurous eaters. Everyone found satisfaction without compromise.\n\nThe pool decks offered activity without Icon's extreme crowds. The Reef Family Splash Zone kept our younger niece entertained. The adults-only Sanctuary gave grandparents refuge. The sports court, mini-golf, and fitness center provided variety.\n\nFor families considering their first mega-ship: Sun Princess proves you don't sacrifice Princess sophistication for scale. She delivers variety without chaos, excitement without carnival atmosphere. Our teenagers enjoyed the experience. We'd actually cruise her again\u2014high praise for family travel.\n\n**The lesson:** Multi-generational travel works when the ship works harder than your family does.",
      "author": {
        "name": "The Mitchell Family",
        "location": "Austin, TX"
      }
    },
    {
      "title": "Solo on the Sphere: Independence Meets Innovation",
      "persona_label": "Solo Experience",
      "persona": "solo",
      "intended_reader": "Solo travelers evaluating new mega-ships",
      "core_insight": "Sun Princess welcomes solo travelers with technology and variety that eliminate typical mega-ship loneliness",
      "markdown": "**As a solo traveler, mega-ships usually intimidate me\u2014too many couples, too much emphasis on shared experiences. Sun Princess changed my perspective entirely.**\n\nThe MedallionClass technology makes solo cruising dramatically easier. Servers already knew my name and drink preference before I reached the bar. I never waited in awkward lines. The technology streamlined everything that typically makes solo travelers feel conspicuous.\n\nThe ship's size became an asset. Enough venues meant I always found my preferred atmosphere. Want quiet reading? The Sanctuary adults-only area provided peace. Want social energy? The Sphere's bars and lounges offered connection. Want anonymous relaxation? The expansive pool decks allowed blending into crowds.\n\nDining worked surprisingly well solo. The main dining room staff seated me with interesting tablemates when I wanted conversation, at comfortable tables for one when I preferred solitude. The Sphere's lounge seating allowed casual dining without feeling conspicuously alone. Specialty restaurants accommodated solo diners without awkward large-table placement.\n\nThe Sphere itself creates natural social opportunities. Evening entertainment draws crowds who chat casually while waiting for shows. The multi-level space means you can engage or observe based on preference. I met fellow solo travelers simply by attending performances.\n\nPrincess's passenger demographic trends older and more refined than some competing lines. This worked beautifully as a solo traveler in my fifties. Conversations happened naturally over shared interests. Nobody questioned why I was traveling alone with judgment in their voice.\n\nFor solo travelers considering Sun Princess: the scale liberates rather than overwhelms if you embrace the variety. The technology smooths rough edges that typically frustrate independent cruisers. The atmosphere welcomes you. Book confidently.\n\n**The lesson:** Solitude doesn't have to mean isolation.",
      "author": {
        "name": "Amanda Rodriguez",
        "location": "Seattle, WA"
      }
    },
    {
      "title": "Honeymooning on Princess's Newest Ship",
      "persona_label": "Honeymoon",
      "persona": "honeymoon",
      "intended_reader": "Newlyweds planning honeymoon cruises",
      "core_insight": "Sun Princess balances romantic intimacy with exciting new experiences perfect for honeymoons",
      "markdown": "**We wanted our honeymoon to feel special\u2014not just another cruise. Sun Princess delivered: brand new ship, revolutionary design, romantic atmosphere without stuffy formality.**\n\nBeing among the first to experience the Sphere Class added excitement beyond typical honeymoon travel. We were exploring Princess's future together. The newness of our marriage matched the newness of the ship. Sounds sentimental, but the parallel created meaningful symbolism.\n\nOur balcony stateroom became our private sanctuary. Morning coffee watching sunrise over the Caribbean. Evening champagne as the ship sailed toward sunset. Room service breakfast in bed without schedule pressure. The space felt intimate despite the ship's massive size.\n\nThe Sanctuary adults-only retreat justified its modest fee immediately. Lounging together, reading, simply being newlywed without children or distractions. Attentive service brought drinks and light meals. The peace contrasted beautifully with the Sphere's evening energy.\n\nDinner became nightly celebration. We rotated between specialty venues\u2014Crown Grill for exceptional steaks, Sabatini's for romantic Italian dining, the Catch for fresh seafood. Each restaurant elevated the experience above standard cruise dining. Every night felt special.\n\nThe Sphere's evening entertainment created shared experiences we'll remember. Immersive shows with stunning visuals. Live music in intimate venues. The variety meant something new every night while maintaining romantic atmosphere.\n\nFor engaged couples planning: Sun Princess combines intimacy with adventure perfectly. The ship's newness adds excitement. The scale provides variety. The Princess service maintains romance. Our honeymoon exceeded expectations\u2014yours could too.\n\n**The lesson:** The best honeymoon teaches partnership through both joy and challenge.",
      "author": {
        "name": "Marcus and Elena Chen",
        "location": "San Francisco, CA"
      }
    },
    {
      "title": "Cruising at 78: Sun Princess Accessibility and Comfort",
      "persona_label": "Senior Travel",
      "persona": "elderly",
      "intended_reader": "Travelers in their 70s and 80s considering mega-ship cruises",
      "core_insight": "Sun Princess accommodates elderly travelers with thoughtful design despite mega-ship scale",
      "markdown": "**At seventy-eight, I wondered if Sun Princess's mega-ship scale would overwhelm me. Instead, thoughtful design made her among the most comfortable ships I've experienced.**\n\nMy primary concern was walking distances. Mega-ships can exhaust elderly passengers forced to trek excessive distances. Sun Princess's layout minimized this. Elevators appeared where needed. Key venues clustered logically. The MedallionClass technology meant no fumbling with cards\u2014everything touchless, which matters for arthritic hands.\n\nThe Sphere created wonderful people-watching opportunities without requiring activity. I'd settle into a comfortable chair with coffee and simply observe the world passing by. Three decks of humanity living their lives around me. Entertainment happened naturally without forcing participation.\n\nDining accommodated my pace beautifully. No rushing through meals. Servers brought courses when I was ready, not on rigid schedules. Special dietary needs handled without fuss\u2014low sodium, soft textures when needed. The main dining room staff learned my preferences quickly and anticipated needs.\n\nThe Sanctuary provided perfect daytime refuge. Comfortable loungers, attentive service, peaceful atmosphere. I could read, nap, or simply sit without noise or chaos. For elderly travelers, having adult-only space matters tremendously.\n\nMedical facilities provided peace of mind. I needed the ship's doctor for a minor issue\u2014seen promptly, treated professionally, medications dispensed quickly. Knowing medical support existed allowed relaxation rather than anxiety.\n\nEntertainment suited my preferences without forcing younger demographics' pace. Live music in comfortable venues. Shows that ended at reasonable hours. Movies with proper seating. No pressure to stay up late or dance energetically.\n\nFor fellow travelers in their seventies and beyond: don't let Sun Princess's size intimidate you. Thoughtful design accommodates our needs. The experience remains accessible and enjoyable. Age adds appreciation rather than obstacle.\n\n**The lesson:** Age is irrelevant when service means respect.",
      "author": {
        "name": "Margaret Sullivan",
        "location": "Phoenix, AZ"
      }
    },
    {
      "title": "Traveling After Loss: Finding Joy on Sun Princess",
      "persona_label": "Widow Travel",
      "persona": "widow",
      "intended_reader": "Widows and widowers considering return to travel",
      "core_insight": "Sun Princess provides supportive environment for those traveling alone after losing partners",
      "markdown": "**My husband and I planned to cruise Sun Princess together\u2014he passed three months before our booking. I nearly cancelled. Instead, I went alone and found that joy and grief can coexist.**\n\nThe decision to travel solo after loss felt impossible. Every cruise memory included him. The thought of experiencing Princess's newest ship without my partner seemed unbearable. But staying home felt worse\u2014he would have wanted me to live.\n\nSun Princess held space for both emotions. The Sphere's beauty brought tears and wonder simultaneously. Sunset from my balcony felt both heartbreaking and magnificent. The ocean's vastness contextualized loss while affirming life's continuation.\n\nThe crew's warmth helped tremendously. Servers who noticed I dined alone treated me with kindness rather than pity. Tablemates who learned my story offered gentle understanding. The community formed organically among other solo travelers, some also widowed.\n\nSurprisingly, the ship's newness helped. This wasn't a vessel we'd sailed together. No haunted memories of shared experiences here. Sun Princess represented new experiences, honoring him by continuing to live rather than merely existing.\n\nThe variety mattered for grief management. When sadness overwhelmed, I could change venues, find different atmosphere, discover distraction. When wanting to feel close to his memory, I'd sit quietly with his favorite whisky and remember.\n\nBy voyage end, something shifted. Not healing\u2014too simple a word for complex grief. But possibility returned. Travel could continue, changed but not ended. Sun Princess helped me see that honoring his memory means living fully, not retreating.\n\nFor fellow widows and widowers: when ready\u2014only when ready\u2014consider traveling again. Ships like Sun Princess provide community when solitude overwhelms. Joy and grief coexist. Life continues, beautiful and painful together.\n\n**The lesson:** Grief needs beautiful places to breathe.",
      "author": {
        "name": "Patricia Henderson",
        "location": "Scottsdale, AZ"
      }
    },
    {
      "title": "Wheelchair Accessible Innovation on Sun Princess",
      "persona_label": "Accessible Travel",
      "persona": "accessible",
      "intended_reader": "Travelers with mobility limitations evaluating new ships",
      "core_insight": "Sun Princess incorporates comprehensive accessibility features designed into the newest Princess ship",
      "markdown": "**As a wheelchair user, I approach new ships with cautious optimism. Sun Princess exceeded expectations\u2014accessibility designed in rather than retrofitted.**\n\nThe difference between accessible-by-compliance and genuinely accessible became immediately clear. Our accessible stateroom wasn't just regulation-compliant\u2014it was thoughtfully designed. Roll-in shower with excellent grab bars, lowered closet rods, generous turning radius, and most importantly, a balcony I could actually access. The threshold worked for my chair.\n\nThe Sphere created accessibility challenges and triumphs. The multi-level space required thought for wheelchair navigation, but elevators appeared strategically. Most viewing areas accommodated wheelchairs without relegating us to rear corners. Some restaurant seating areas in the Sphere worked better than others, but staff solved problems quickly.\n\nPublic spaces generally accommodated movement well. Thresholds between venues remained manageable. Theater seating for wheelchairs provided decent views\u2014not perfect, but better than many ships. The buffet layout allowed independent access without requiring assistance for every plate.\n\nMedallionClass technology helped tremendously. Touchless everything meant fewer physical interactions required. Ordering food and drinks through the app eliminated navigating crowded bars. Wayfinding features helped route me through accessible paths.\n\nShore excursions required research as always, but Sun Princess offered wheelchair-accessible tours at most ports. Tender ports proved challenging, though crew assistance made them possible with patience. Being among the first to sail meant some accessibility details still needed refinement\u2014feedback was welcomed.\n\nCrew attitude mattered most. Staff treated me as guest rather than problem. Assistance came without condescension. Questions about needs felt respectful, never intrusive. The cultural approach to accessibility matters as much as physical design.\n\nFor fellow travelers with mobility challenges: Sun Princess works well. Not perfectly\u2014no ship achieves that\u2014but genuinely accommodating. As Princess's newest class, she incorporates accessibility better than retrofitted vessels. Cruise confidently.\n\n**The lesson:** Accessibility means equal dignity, not special treatment.",
      "author": {
        "name": "David Martinez",
        "location": "Tampa, FL"
      }
    },
    {
      "title": "A Veteran's Perspective: Sun Princess Excellence",
      "persona_label": "Military Travel",
      "persona": "veteran",
      "intended_reader": "Military veterans evaluating cruise options",
      "core_insight": "Sun Princess offers the scale and efficiency veterans appreciate in well-run operations",
      "markdown": "**Twenty years Navy taught me to recognize well-run operations. Sun Princess demonstrates operational excellence at impressive scale.**\n\nMilitary service creates appreciation for systems that work. The MedallionClass technology operating across a vessel carrying 4,300 guests impressed me enormously. Touchless everything. Location awareness. Personalized service enabled by data. The logistics rival military operations but focused on comfort rather than combat.\n\nThe crew's professionalism reminded me of good military units. Everyone knew their role. Handoffs between departments happened seamlessly. Problems got solved quickly without excuses. The ship operated with precision that veterans recognize and appreciate.\n\nWhat struck me most: the Sphere's technical complexity managed so smoothly. Multiple dining venues, entertainment systems, lighting, and audio all orchestrated simultaneously across three decks. The coordination required staggers the imagination. Yet it appeared effortless to guests.\n\nThe vessel's scale demanded efficient operations, and Sun Princess delivered. Embarkation processed thousands smoothly. Dining served everyone excellently despite volume. Safety drills demonstrated competence. The operation runs well because someone designed systems thoughtfully.\n\nFor fellow veterans who appreciate well-run organizations: Sun Princess demonstrates how good operations enhance experience. The cruise line's attention to detail, training, and systems shows throughout. Military service teaches you to spot quality operations\u2014Sun Princess qualifies.\n\nAlso worth noting: Princess honors military service with veteran recognition programs. While I don't cruise for discounts, the respect shown matters. The culture values service members' contributions.\n\n**The lesson:** Experience teaches discernment.",
      "author": {
        "name": "Commander James Wilson, USN (Ret.)",
        "location": "Virginia Beach, VA"
      }
    },
    {
      "title": "Mediterranean Dreams on Princess's Flagship",
      "persona_label": "Adventure Seeker",
      "persona": "adventure",
      "intended_reader": "Travelers seeking destination-focused experiences on new ships",
      "core_insight": "Sun Princess combines destination immersion with cutting-edge ship innovation",
      "markdown": "**We chose Sun Princess specifically for Mediterranean itineraries\u2014experiencing Princess's newest ship while exploring ancient destinations created perfect balance.**\n\nThe Mediterranean demands a certain ship. Too small, you lack amenities for sea days. Too focused on onboard attractions, the ship competes with destinations rather than complementing them. Sun Princess hit the balance beautifully.\n\nSea days showcased the Sphere brilliantly. When weather kept us inside, the three-deck atrium provided entertainment and variety without feeling confined. The immersive shows created experiences worthy of European theaters. We didn't resent sea days\u2014they became experiences themselves.\n\nPort days balanced perfectly. Sun Princess's size meant she navigated Mediterranean harbors efficiently. We weren't among those mega-ships anchoring offshore and tendering endlessly. Early departure meant maximum time ashore exploring Rome, Barcelona, or Greek islands.\n\nReturning to the ship after intensive sightseeing felt like coming home. The Sanctuary provided recovery space after walking ancient ruins all day. Specialty dining delivered exceptional meals after lunches of tourist-trap food. The balcony offered quiet reflection processing cultural experiences.\n\nThe MedallionClass technology streamlined port days. No fumbling with cruise cards at gangway. No waiting in long lines. Simply walk off the ship, explore, return when ready. The efficiency maximized shore time.\n\nFor destination-focused travelers: Sun Princess enhances rather than distracts from ports. She's impressive enough to appreciate but not so attraction-heavy that you resent leaving the ship. Mediterranean itineraries showcase both the ship's capabilities and the destinations' magnificence.",
      "author": {
        "name": "Nicole and Robert Torres",
        "location": "Chicago, IL"
      }
    },
    {
      "title": "Worth the Premium: Why We Chose Sun Princess for Anniversary Luxury",
      "persona_label": "Luxury Couples",
      "persona": "couples",
      "intended_reader": "Couples seeking premium cruise experiences without ultra-luxury pricing",
      "core_insight": "Sun Princess delivers sophisticated luxury at premium mass-market pricing",
      "markdown": "**Our twenty-fifth anniversary deserved something special. We considered ultra-luxury lines but chose Sun Princess\u2014Princess's finest ship at premium-but-not-absurd pricing.**\n\nThe calculation was simple: ultra-luxury lines charge $1,000+ per person per night. Sun Princess in a Sky Suite ran roughly $400 per person per night including Princess Plus. For our budget, that meant longer voyage, better stateroom, and money remaining for exceptional shore excursions.\n\nOur Sky Suite exceeded expectations completely. Over 700 square feet with separate living area, large balcony, premium bathroom, and priority everything. The space rivaled boutique hotel suites at Mediterranean destinations. Room service delivered meals that competed with specialty restaurants.\n\nThe Sanctuary's adults-only atmosphere provided luxury-line tranquility. Attentive service, premium food and drinks, comfortable loungers, and peaceful escape from families. For $70 per person for the week, we gained daily luxury retreat that ultra-luxury lines include but we accessed affordably.\n\nSpecialty dining delivered food worthy of significantly higher prices. Crown Grill's steaks competed with land-based steakhouses charging triple. Sabatini's Italian cuisine showcased proper technique and quality ingredients. The Catch served seafood that honored its ingredients rather than drowning them in sauce.\n\nThe Sphere provided entertainment exceeding many land-based theaters. Production quality, technical capabilities, and performer talent justified the ticket prices we'd pay on land\u2014but were included in our cruise fare.\n\nFor couples seeking sophisticated luxury without ultra-luxury pricing: Sun Princess delivers. She's not Regent or Seabourn\u2014she's Princess elevated to its highest expression. If you appreciate quality service, fine dining, and elegant atmosphere without requiring caviar and butlers, Sun Princess provides exceptional value.",
      "author": {
        "name": "Jonathan and Catherine Park",
        "location": "San Diego, CA"
      }
    },
    {
      "title": "First Cruise on Princess's Revolutionary Ship",
      "persona_label": "First Cruise Experience",
      "persona": "first-timer",
      "intended_reader": "First-time cruisers attracted to groundbreaking vessels",
      "core_insight": "Sun Princess proves that revolutionary scale can still feel welcoming to nervous first-timers",
      "markdown": "**Everyone said a Sphere Class ship was too ambitious for a first cruise. Too big. Too innovative. Too much. Sun Princess proved that thoughtful design makes even revolutionary ships accessible to complete newcomers.**\n\nMy concerns multiplied with Sun Princess's size. At 175,500 tons, she carried more passengers than my hometown's population. Would I get lost for days? Would the technology overwhelm before it helped? Would I feel like a number rather than a guest?\n\nThe MedallionClass technology answered every worry. From embarkation through disembarkation, the Medallion guided me everywhere. Doors opened automatically. The app showed me where to go. Crew members greeted me by name before I could feel anonymous. The technology that seemed intimidating became liberating.\n\nThe Sphere provided unexpected orientation. That soaring venue served as my anchor point: find the Sphere, and everything else made sense. The revolutionary architecture functioned as navigation aid, not just spectacle.\n\nDining options seemed overwhelming until I realized flexibility was the point. Traditional dining when I wanted structure. Casual venues when I didn't. The variety reduced pressure rather than creating it.\n\nBy mid-voyage, I'd stopped feeling like a first-timer. Sun Princess had absorbed me into her rhythms so smoothly that size became irrelevant. The ship felt like a neighborhood I'd learned to navigate rather than a city that overwhelmed.\n\nSun Princess didn't just give me a first cruise. She gave me confidence that I could handle anything cruising offered.\n\n**The lesson:** Revolutionary doesn't have to mean intimidating when design serves guests rather than impresses them.",
      "author": {
        "name": "Rebecca Morrison",
        "location": "Phoenix, AZ"
      }
    },
    {
      "title": "Celebrating Against All Odds",
      "persona_label": "Survival Celebration",
      "persona": "special-occasion",
      "intended_reader": "Those celebrating survival or major life achievements",
      "core_insight": "Sun Princess crew understands that some celebrations honor survival as much as achievement",
      "markdown": "**Five years cancer-free deserved celebration. Not just a dinner. Not just acknowledgment. Sun Princess gave us the ceremony our survival had earned.**\n\nWe'd mentioned my five-year milestone when booking, unsure what response to expect. What unfolded reminded us that Princess understands what survival means to those who've faced death.\n\nOur cabin awaited with flowers and a card referencing our survival journey. Someone had actually read what we'd shared during booking. The hotel director's note acknowledged not just my survival but my husband's partnership through treatment.\n\nThe Sphere became our celebration venue in ways we hadn't anticipated. Watching shows in that revolutionary space felt appropriately grand for a life reclaimed. We held hands through performances, grateful to be anywhere together, astonished to be somewhere this beautiful.\n\nDinner on my cancerversary became sacred. The maitre d' arranged a table overlooking the ship's wake. The chef prepared dishes I'd craved during treatment but couldn't eat. Each course celebrated food as pleasure rather than medicine.\n\nThe crew sang, but their song felt different from standard celebrations. They'd learned our story. The music honored survival specifically. Fellow passengers, learning what we were celebrating, rose to applaud. Strangers understood what five years meant.\n\nSun Princess gave us ceremony worthy of what we'd survived. The newest ship honored the oldest human triumph: being alive against odds that had once seemed impossible.\n\n**The lesson:** Some celebrations honor surviving what tried to destroy us as much as achieving what we attempted.",
      "author": {
        "name": "Catherine and Michael Torres",
        "location": "Denver, CO"
      }
    },
    {
      "title": "The Sphere as Sanctuary",
      "persona_label": "Recovery Journey",
      "persona": "healing",
      "intended_reader": "Those seeking healing through beauty and innovation",
      "core_insight": "Sun Princess offers healing through revolutionary beauty that demands presence",
      "markdown": "**Grief had flattened my world. After my daughter's death, beauty felt irrelevant at best, cruel at worst. Sun Princess taught me that revolutionary beauty could demand attention that ordinary beauty couldn't penetrate.**\n\nThe loss of a child changes everything. Colors fade. Music grates. The beautiful things that once brought joy become reminders of who isn't there to share them. My therapist suggested overwhelming beauty, something so vast it might penetrate grief's defenses.\n\nSun Princess's Sphere accomplished what my therapist described. That soaring entertainment venue stopped me in my tracks the first time I entered. The architecture demanded attention. Grief couldn't compete with that scale of beauty. For moments at a time, I was simply present.\n\nI spent hours in the Sphere, watching light change through the glass dome. Not thinking about my daughter. Not not thinking about her. Just being present with something beautiful enough to hold my attention despite grief's pull.\n\nThe innovation throughout Sun Princess served similar function. MedallionClass technology created small moments of wonder. The ship's scale contextualized my loss: enormous pain against something enormous and beautiful. Both were real. Both were part of life.\n\nI wasn't healed by voyage end. Grief doesn't work that way. But I'd experienced something important: beauty could still reach me. The Sphere had penetrated defenses that smaller beauties couldn't. Revolutionary architecture had accomplished what therapist's offices couldn't.\n\nSun Princess gave me proof that wonder remained possible even in grief's deepest valleys. That proof became foundation for everything that followed.\n\n**The lesson:** Sometimes healing requires beauty so vast it overwhelms grief's defenses.",
      "author": {
        "name": "Margaret Sullivan",
        "location": "Atlanta, GA"
      }
    }
  ]
}