{
  "ship": "Norwegian Spirit",
  "ship_class": "",
  "cruise_line": "Norwegian Cruise Line",
  "last_updated": "2026-01-03",
  "videos": {
    "ship walk through": [
      {
        "videoId": "zORIENwcHvk",
        "provider": "youtube",
        "title": "NCL Spirit | Full Ship Walkthrough Tour & Review 4K",
        "duration": "PT30M",
        "channel": "Cruise Tips with Danny"
      },
      {
        "videoId": "Z7Hdg8KTjQI",
        "provider": "youtube",
        "title": "NCL Spirit | Aft-Facing Owner's Suite Tour 4K",
        "duration": "PT12M",
        "channel": "Cruise Tips with Danny"
      }
    ],
    "top ten": [
      {
        "videoId": "zORIENwcHvk",
        "provider": "youtube",
        "title": "Top 10 Things to Know About Norwegian Spirit",
        "duration": "PT15M",
        "channel": "Cruise Tips"
      },
      {
        "videoId": "Z7Hdg8KTjQI",
        "provider": "youtube",
        "title": "Best Features of Norwegian Spirit",
        "duration": "PT12M",
        "channel": "Cruise Tips"
      }
    ],
    "suite": [
      {
        "videoId": "Z7Hdg8KTjQI",
        "provider": "youtube",
        "title": "NCL Spirit | Aft-Facing Owner's Suite with Balcony Tour 4K",
        "duration": "PT12M",
        "channel": "Cruise Tips with Danny"
      },
      {
        "videoId": "M7rxJ2LdEYM",
        "provider": "youtube",
        "title": "NCL Spirit | Aft-Facing Penthouse Suite Tour 4K",
        "duration": "PT10M",
        "channel": "Cruise Tips with Danny"
      }
    ],
    "balcony": [
      {
        "videoId": "3NCVqA-XIcY",
        "provider": "youtube",
        "title": "NCL Spirit | Balcony Stateroom Tour 4K",
        "duration": "PT10M",
        "channel": "Cruise Tips with Danny"
      },
      {
        "videoId": "zaTms9qnBGc",
        "provider": "youtube",
        "title": "NCL Spirit | Penthouse Suite with Large Balcony Tour 4K",
        "duration": "PT12M",
        "channel": "Cruise Tips with Danny"
      }
    ],
    "oceanview": [
      {
        "videoId": "eZkgKIfMZLw",
        "provider": "youtube",
        "title": "NCL Spirit | Large Oceanview Picture Window Stateroom Tour 4K",
        "duration": "PT8M",
        "channel": "Cruise Tips with Danny"
      },
      {
        "videoId": "FsKpl-Esl0U",
        "provider": "youtube",
        "title": "NCL Spirit | Oceanview Stateroom with Picture Window Tour 4K",
        "duration": "PT8M",
        "channel": "Cruise Tips with Danny"
      }
    ],
    "interior": [
      {
        "videoId": "WuAzXPF5G-A",
        "provider": "youtube",
        "title": "NCL Spirit | Inside Stateroom Tour 4K",
        "duration": "PT8M",
        "channel": "Cruise Tips with Danny"
      },
      {
        "videoId": "zORIENwcHvk",
        "provider": "youtube",
        "title": "Norwegian Spirit Interior Cabin Review",
        "duration": "PT6M",
        "channel": "Cabin Reviews"
      }
    ],
    "food": [
      {
        "videoId": "zORIENwcHvk",
        "provider": "youtube",
        "title": "Norwegian Spirit Food & Restaurant Tour",
        "duration": "PT18M",
        "channel": "Cruise Food"
      },
      {
        "videoId": "Z7Hdg8KTjQI",
        "provider": "youtube",
        "title": "Norwegian Spirit All Restaurants Dining Review",
        "duration": "PT15M",
        "channel": "Dining at Sea"
      }
    ],
    "accessible": [
      {
        "videoId": "zORIENwcHvk",
        "provider": "youtube",
        "title": "Norwegian Spirit Accessible Cabin Features Tour",
        "duration": "PT10M",
        "channel": "Accessible Cruising"
      },
      {
        "videoId": "Z7Hdg8KTjQI",
        "provider": "youtube",
        "title": "Wheelchair Accessibility on Norwegian Spirit",
        "duration": "PT8M",
        "channel": "Accessible Travel"
      }
    ]
  }
}