{
  "port_slug": "cadiz",
  "port_name": "Cádiz",
  "port_pin": {
    "lat": 36.5333,
    "lon": -6.2833,
    "label": "Cádiz Cruise Terminal"
  },
  "poi_ids": [
    "cadiz-cruise-terminal",
    "cadiz-cathedral",
    "torre-tavira",
    "barrio-del-populo",
    "playa-la-caleta",
    "mercado-central-cadiz"
  ],
  "bbox_hint": {
    "south": 36.52,
    "west": -6.31,
    "north": 36.54,
    "east": -6.28
  },
  "notes": "Compact old town, entirely walkable from port. One of Europe's oldest cities.",
  "generated": "2025-12-14T00:00:00Z"
}
