{
  "_meta": {
    "version": "1.0.0",
    "generated": "2026-01-31T00:00:00Z",
    "source": "auto-extracted from /ports/cape-cod.html"
  },
  "port_slug": "cape-cod",
  "port_name": "Cape Cod",
  "port_pin": {
    "lat": 41.6688,
    "lon": -70.2962,
    "label": "Cape Cod Region"
  },
  "bbox_hint": {
    "south": 41.55,
    "west": -70.6,
    "north": 42.1,
    "east": -69.95,
    "note": "Covers Cape Cod peninsula from Hyannis to Provincetown"
  },
  "poi_ids": [
    "cape-cod-provincetown",
    "cape-cod-race-point",
    "cape-cod-hyannis"
  ]
}
