{
  "alt": "Black-and-white 1866 lithograph showing Spanish ships at left bombarding the Callao shoreline while Peruvian defenders man cannons along an earthwork battery beneath a Peruvian flag at right",
  "dateTaken": "1866",
  "description": "1866 lithograph by L. Cappa depicting the Spanish naval bombardment of Callao and the defense by Peruvian forces at Real Felipe Fortress and the surrounding shore batteries. Library of Congress reproduction number cph.3c36429.",
  "license": "No known restrictions on publication",
  "licenseUrl": "https://www.loc.gov/rr/print/195_copr.html",
  "photographer": "L. Cappa (lithograph artist); LOT 4831, Library of Congress Prints & Photographs Division",
  "reproductionNumber": "LC-USZ62-46473 (cph.3c36429)",
  "sourceUrl": "https://www.loc.gov/item/2006676643/",
  "title": "Bombardment of Callao, May 2, 1866",
  "verifiedBy": "sourcing.py session 2026-05-13",
  "verifiedDate": "2026-05-13"
}
