{
  "alt": "Plate of Peruvian ceviche on turquoise ceramic \u2014 lime-cured white fish with red onion and cilantro topped by a slice of red aj\u00ed chili, served with choclo corn, orange sweet potato slices, toasted corn, and fried fish chunks, with a hand reaching in with a fork from above",
  "dateTaken": "2024",
  "description": "Traditional Peruvian ceviche plated with all the canonical accompaniments: white fish cured in lime juice (leche de tigre), red onion, cilantro, and a slice of red aj\u00ed chili on top \u2014 served with choclo (large-kernel Andean corn), camote (sweet potato), cancha (toasted corn), and chicharr\u00f3n de pescado.",
  "license": "Pexels License",
  "licenseUrl": "https://www.pexels.com/license/",
  "photographer": "Nano Erdozain",
  "sourceUrl": "https://www.pexels.com/photo/gourmet-peruvian-ceviche-with-fried-seafood-28448397/",
  "title": "Gourmet Peruvian Ceviche with Fried Seafood",
  "verifiedBy": "sourcing.py session 2026-05-12",
  "verifiedDate": "2026-05-12"
}
