{
  "title": "File:2019-03-03 Chinstrap penguin on Barrientos Island, Antarctica.jpg",
  "url": "https://upload.wikimedia.org/wikipedia/commons/thumb/7/73/2019-03-03_Chinstrap_penguin_on_Barrientos_Island%2C_Antarctica.jpg/1280px-2019-03-03_Chinstrap_penguin_on_Barrientos_Island%2C_Antarctica.jpg",
  "original_url": "https://upload.wikimedia.org/wikipedia/commons/7/73/2019-03-03_Chinstrap_penguin_on_Barrientos_Island%2C_Antarctica.jpg",
  "license": "CC BY-SA 4.0",
  "license_url": "https://creativecommons.org/licenses/by-sa/4.0",
  "author": "<a href=\"//commons.wikimedia.org/wiki/User:GRDN711\" title=\"User:GRDN711\">Gordon Leggett</a>",
  "description": "Chinstrap penguin (<i>Pygoscelis antarcticus</i>) on Barrientos Island, in Antarctica on March 3, 2019.",
  "commons_url": "https://commons.wikimedia.org/wiki/File%3A2019-03-03%20Chinstrap%20penguin%20on%20Barrientos%20Island%2C%20Antarctica.jpg"
}